gbnf_compiler/__init__.py
gbnf_compiler/compiler.py
gbnf_compiler/rules.py
gbnf_compiler-0.3.2.dist-info/LICENSE
gbnf_compiler-0.3.2.dist-info/METADATA
gbnf_compiler-0.3.2.dist-info/WHEEL
gbnf_compiler-0.3.2.dist-info/RECORD
