Metadata-Version: 2.1
Name: gbnf-compiler
Version: 0.3.2
Summary: Simple plug and play GBNF compiler for llama.cpp
Home-page: https://github.com/nova-land/gbnf-compiler
License: MIT
Author: NovaLand
Author-email: 87605316+nova-land@users.noreply.github.com
Requires-Python: >=3.10
Classifier: License :: OSI Approved :: MIT License
Classifier: Programming Language :: Python :: 3
Classifier: Programming Language :: Python :: 3.10
Classifier: Programming Language :: Python :: 3.11
Classifier: Programming Language :: Python :: 3.12
Project-URL: Repository, https://github.com/nova-land/gbnf-compiler
